MANIFEST.in
README.md
setup.cfg
setup.py
docassemble/__init__.py
docassemble.hmlrhelper.egg-info/PKG-INFO
docassemble.hmlrhelper.egg-info/SOURCES.txt
docassemble.hmlrhelper.egg-info/dependency_links.txt
docassemble.hmlrhelper.egg-info/namespace_packages.txt
docassemble.hmlrhelper.egg-info/not-zip-safe
docassemble.hmlrhelper.egg-info/requires.txt
docassemble.hmlrhelper.egg-info/top_level.txt
docassemble/hmlrhelper/__init__.py
docassemble/hmlrhelper/objects.py
docassemble/hmlrhelper/data/questions/docusignBuilder.yml
docassemble/hmlrhelper/data/questions/docusignQuestions.yml
docassemble/hmlrhelper/data/questions/test.yml
docassemble/hmlrhelper/data/questions/tr1.yml
docassemble/hmlrhelper/data/questions/tr1Output.yml
docassemble/hmlrhelper/data/questions/tr1Questions.yml
docassemble/hmlrhelper/data/sources/README.md
docassemble/hmlrhelper/data/static/README.md
docassemble/hmlrhelper/data/templates/README.md
docassemble/hmlrhelper/data/templates/TR1__2019-06-17_.pdf