Metadata-Version: 2.1
Name: docassemble.hmlrhelper
Version: 0.0.3
Summary: A docassemble extension that allows you to submit HM Land Registry (HMLR) forms to DocuSign
Home-page: https://tonic.works
Author: Matt Pennington
Author-email: mp@tonic.works
License: The MIT License (MIT)
Platform: UNKNOWN
